setup.py
bytom/__init__.py
bytom/bind.py
bytom/client.py
bytom/models.py
bytom/rpc.py
bytom/signatures/__init__.py
bytom/signatures/derivexpub.py
bytom/signatures/ed25519.py
bytom/signatures/expandedprivatekey.py
bytom/signatures/finddst.py
bytom/signatures/nonhardenedchild.py
bytom/signatures/signatures.py
bytom/signatures/signer.py
bytom/signatures/utils.py
python_bytom.egg-info/PKG-INFO
python_bytom.egg-info/SOURCES.txt
python_bytom.egg-info/dependency_links.txt
python_bytom.egg-info/requires.txt
python_bytom.egg-info/top_level.txt
python_bytom.egg-info/zip-safe
tests/__init__.py
tests/test_api_request.py
tests/test_signatures.py
tests/test_signatures_component.py