Metadata-Version: 1.1
Name: python-bytom
Version: 1.0.3
Summary: Bytom Python SDK
Home-page: https://github.com/Bytom-Community/python-bytom
Author: cnfuyu
Author-email: cnfuyu@gmail.com
License: MIT
Keywords: bytom python sdk api wallet
Platform: UNKNOWN
Classifier: Intended Audience :: Developers
Classifier: License :: OSI Approved :: MIT License
Classifier: Operating System :: OS Independent
Classifier: Programming Language :: Python :: 2
Classifier: Programming Language :: Python :: 2.7
Classifier: Programming Language :: Python :: 3
Classifier: Programming Language :: Python :: 3.4
Classifier: Programming Language :: Python :: 3.5
Classifier: Programming Language :: Python :: 3.6
Classifier: Programming Language :: Python
Classifier: Topic :: Software Development :: Libraries :: Python Modules
